scount/__init__.py
scount/sourcelines.py
scount-0.3.0.dist-info/LICENSE
scount-0.3.0.dist-info/METADATA
scount-0.3.0.dist-info/WHEEL
scount-0.3.0.dist-info/entry_points.txt
scount-0.3.0.dist-info/RECORD
